mirakl_lib/__init__.py
mirakl_lib/client.py
mirakl_lib/order.py
mirakl_lib/response.py
mirakl_lib-0.1.1.dist-info/METADATA
mirakl_lib-0.1.1.dist-info/WHEEL
mirakl_lib-0.1.1.dist-info/top_level.txt
mirakl_lib-0.1.1.dist-info/RECORD
