Metadata-Version: 2.1
Name: mirakl-lib
Version: 0.1.1
Summary: A package for interacting with the Mirakl API
Home-page: UNKNOWN
Author: Samuel Benning
Author-email: bensam1993@gmail.com
License: UNKNOWN
Platform: UNKNOWN
Classifier: Programming Language :: Python :: 3
Classifier: License :: OSI Approved :: MIT License
Classifier: Operating System :: OS Independent
Requires-Python: >=3.6
Requires-Dist: pydantic
Requires-Dist: requests
Requires-Dist: typing
